venv/bin/activate_this.py
vorbote/__init__.py
vorbote/annotation.py
vorbote/app.py
vorbote/config.py
vorbote/parse.py
vorbote/schema.py
vorbote/filter/__init__.py
vorbote/filter/git.py
vorbote/schemas/annotations.schema
vorbote/schemas/config.schema
vorbote/templates/.gitkeep
vorbote/templates/changes.md.j2
vorbote/templates/changes.tex.j2
vorbote-1.0.0.dist-info/licenses/LICENSE
vorbote-1.0.0.dist-info/METADATA
vorbote-1.0.0.dist-info/WHEEL
vorbote-1.0.0.dist-info/entry_points.txt
vorbote-1.0.0.dist-info/top_level.txt
vorbote-1.0.0.dist-info/RECORD
