Metadata-Version: 2.4
Name: vorbote
Version: 1.0.0
Summary: Communicate releases/changes via Git annotations
Author-email: rmk2 <ryko@rmk2.org>
License-Expression: Apache-2.0
Project-URL: Repository, https://gitlab.com/rmk2/vorbote
Requires-Python: >=3.13
License-File: LICENSE
Requires-Dist: gitpython~=3.1
Requires-Dist: jinja2~=3.1
Requires-Dist: pyyaml~=6.0
Requires-Dist: jsonschema~=4.17
Requires-Dist: tomli~=2.0
Requires-Dist: skabelon~=1.0
Dynamic: license-file
